{
  "src_dir"            :   "build/",
  "access_key"         :   "TTqnR6c0UGsDHFlXH03532_guq-e0yB40kGLiMDz",
  "secret_key"         :   "3RrCr4P20tPBluQnpQi8ColP42I4tInecKLVOGkR",
  "bucket"             :   "jhrfile1",
  "ignore_dir"         :   false,
  "key_prefix"         :   "jiuhuar/mall/",
  "overwrite"          :   false,
  "check_exists"       :   false,
  "check_hash"         :   false,
  "check_size"         :   false,
  "skip_file_prefixes" :   ".git,bin",
  "skip_fixed_strings" :   ".svn",
  "skip_suffixes"      :   ".DS_Store,.exe",
  "rescan_local"       :   true,
  "log_file"           :   "upload.log",
  "log_level"          :   "info"
}
